[
  {
    "obj_attr": "static",
    "obj_id": "03",
    "obj_type": "Motorcycle",
    "psr": {
      "position": {
        "x": 7.893382256822012,
        "y": 8.027411640339531,
        "z": -1.3742097472240098
      },
      "rotation": {
        "x": 0,
        "y": 0,
        "z": 1.63859725251189
      },
      "scale": {
        "x": 1.7560105291658339,
        "y": 0.6176567808215415,
        "z": 1.4463313722557898
      }
    }
  },
  {
    "obj_attr": "static",
    "obj_id": "04",
    "obj_type": "Scooter",
    "psr": {
      "position": {
        "x": 8.493527485323877,
        "y": 8.039706278570296,
        "z": -1.4739941906902727
      },
      "rotation": {
        "x": 0,
        "y": 0,
        "z": 1.5831283448605578
      },
      "scale": {
        "x": 1.4274993518149741,
        "y": 0.6499615619001272,
        "z": 1.4463313722557898
      }
    }
  },
  {
    "obj_attr": "static",
    "obj_id": "05",
    "obj_type": "Motorcycle",
    "psr": {
      "position": {
        "x": 9.395559296980167,
        "y": 8.073152516544345,
        "z": -1.4543268632862505
      },
      "rotation": {
        "x": 0,
        "y": 0,
        "z": 1.596976265574812
      },
      "scale": {
        "x": 1.7147117473321813,
        "y": 0.685868544633218,
        "z": 1.4463313722557898
      }
    }
  },
  {
    "obj_attr": "static",
    "obj_id": "06",
    "obj_type": "Motorcycle",
    "psr": {
      "position": {
        "x": 10.081506815095288,
        "y": 8.194541258246376,
        "z": -1.4227805768893163
      },
      "rotation": {
        "x": 0,
        "y": 0,
        "z": 1.603557216170279
      },
      "scale": {
        "x": 1.4603341922656679,
        "y": 0.5792716411108076,
        "z": 1.4463313722557898
      }
    }
  },
  {
    "obj_attr": "static",
    "obj_id": "21",
    "obj_type": "Motorcycle",
    "psr": {
      "position": {
        "x": -4.888682003514879,
        "y": 7.634604468782555,
        "z": -1.2177013184993992
      },
      "rotation": {
        "x": 0,
        "y": 0,
        "z": 1.6970873641288893
      },
      "scale": {
        "x": 1.4708791774739836,
        "y": 0.5946851859092859,
        "z": 1.4463313722557898
      }
    }
  },
  {
    "obj_attr": "static",
    "obj_id": "22",
    "obj_type": "Motorcycle",
    "psr": {
      "position": {
        "x": -5.402348069219661,
        "y": 7.596667510833124,
        "z": -1.2886207095601416
      },
      "rotation": {
        "x": 0,
        "y": 0,
        "z": 1.7153486201587531
      },
      "scale": {
        "x": 1.5925615329297618,
        "y": 0.6773649396567644,
        "z": 1.3138014061884598
      }
    }
  },
  {
    "obj_attr": "static",
    "obj_id": "23",
    "obj_type": "Motorcycle",
    "psr": {
      "position": {
        "x": -6.1554064737577345,
        "y": 7.657771693897315,
        "z": -1.2718483744793159
      },
      "rotation": {
        "x": 0,
        "y": 0,
        "z": 1.7824613495197974
      },
      "scale": {
        "x": 1.4450169472012013,
        "y": 0.6384391179581896,
        "z": 1.280256736026808
      }
    }
  },
  {
    "obj_attr": "static",
    "obj_id": "24",
    "obj_type": "Motorcycle",
    "psr": {
      "position": {
        "x": -6.973967500442345,
        "y": 7.607053771113158,
        "z": -1.254705095033742
      },
      "rotation": {
        "x": 0,
        "y": 0,
        "z": 1.7631019928103346
      },
      "scale": {
        "x": 1.3574321385735073,
        "y": 0.6042527123839796,
        "z": 1.2636492724039097
      }
    }
  },
  {
    "obj_attr": "static",
    "obj_id": "25",
    "obj_type": "Motorcycle",
    "psr": {
      "position": {
        "x": -7.614048504754272,
        "y": 7.576395636728844,
        "z": -1.2517344885505055
      },
      "rotation": {
        "x": 0,
        "y": 0,
        "z": 1.661794873859279
      },
      "scale": {
        "x": 1.4477063763571538,
        "y": 0.595171280716005,
        "z": 1.2138268815352153
      }
    }
  },
  {
    "obj_attr": "static",
    "obj_id": "26",
    "obj_type": "Motorcycle",
    "psr": {
      "position": {
        "x": -8.364058451020506,
        "y": 7.613364941276699,
        "z": -1.2517344885505055
      },
      "rotation": {
        "x": 0,
        "y": 0,
        "z": 1.7555214208721097
      },
      "scale": {
        "x": 1.599809402586291,
        "y": 0.6700280600583527,
        "z": 1.2138268815352153
      }
    }
  },
  {
    "obj_attr": "static",
    "obj_id": "30",
    "obj_type": "Motorcycle",
    "psr": {
      "position": {
        "x": -2.3945063889085714,
        "y": 7.900104992010619,
        "z": -1.2729450558608635
      },
      "rotation": {
        "x": 0,
        "y": 0,
        "z": 1.387536755335492
      },
      "scale": {
        "x": 1.4776523683221623,
        "y": 0.743576231448725,
        "z": 1.3225907787874038
      }
    }
  },
  {
    "obj_attr": "static",
    "obj_id": "31",
    "obj_type": "Motorcycle",
    "psr": {
      "position": {
        "x": -1.4449638259245228,
        "y": 7.6495927726995685,
        "z": -1.2932583644484992
      },
      "rotation": {
        "x": 0,
        "y": 0,
        "z": 1.4398966328953218
      },
      "scale": {
        "x": 1.5064282407178629,
        "y": 0.6730795844384116,
        "z": 1.4463313722557898
      }
    }
  },
  {
    "obj_attr": "static",
    "obj_id": "32",
    "obj_type": "Motorcycle",
    "psr": {
      "position": {
        "x": 0.0023595139229127425,
        "y": 7.646085038101199,
        "z": -1.2252463428769544
      },
      "rotation": {
        "x": 0,
        "y": 0,
        "z": 1.4398966328953218
      },
      "scale": {
        "x": 1.6078855978559374,
        "y": 0.6880825346783968,
        "z": 1.4722100946637215
      }
    }
  },
  {
    "obj_attr": "static",
    "obj_id": "33",
    "obj_type": "Motorcycle",
    "psr": {
      "position": {
        "x": 0.5474606625588285,
        "y": 8.168324493054833,
        "z": -1.2932583644484992
      },
      "rotation": {
        "x": 0,
        "y": 0,
        "z": 1.6428983360486047
      },
      "scale": {
        "x": 1.7290745404254177,
        "y": 0.6930499411798362,
        "z": 1.4463313722557898
      }
    }
  },
  {
    "obj_attr": "static",
    "obj_id": "34",
    "obj_type": "Motorcycle",
    "psr": {
      "position": {
        "x": 1.3207711347497724,
        "y": 7.801335297894197,
        "z": -1.2932583644484992
      },
      "rotation": {
        "x": 0,
        "y": 0,
        "z": 1.5652206193868685
      },
      "scale": {
        "x": 1.4494542943305329,
        "y": 0.5243761913715697,
        "z": 1.4463313722557898
      }
    }
  },
  {
    "obj_attr": "static",
    "obj_id": "35",
    "obj_type": "Motorcycle",
    "psr": {
      "position": {
        "x": 2.513118226343018,
        "y": 7.978538390574659,
        "z": -1.3450158092643627
      },
      "rotation": {
        "x": 0,
        "y": 0,
        "z": 1.591114323041763
      },
      "scale": {
        "x": 1.4130930923742189,
        "y": 0.5712593717738074,
        "z": 1.3428164826240627
      }
    }
  },
  {
    "obj_attr": "static",
    "obj_id": "43",
    "obj_type": "Motorcycle",
    "psr": {
      "position": {
        "x": -13.963906799893614,
        "y": -6.644904357573058,
        "z": -1.1509253912048745
      },
      "rotation": {
        "x": 0,
        "y": 0,
        "z": -1.6049119755869974
      },
      "scale": {
        "x": 1.5195979688470616,
        "y": 0.5959756481103765,
        "z": 1.1616654257685404
      }
    }
  },
  {
    "obj_attr": "static",
    "obj_id": "44",
    "obj_type": "Motorcycle",
    "psr": {
      "position": {
        "x": -14.699017222549697,
        "y": -6.4720726704401565,
        "z": -1.073358810269026
      },
      "rotation": {
        "x": 0,
        "y": 0,
        "z": -1.568706372325062
      },
      "scale": {
        "x": 1.3549927220580602,
        "y": 0.5351432685859877,
        "z": 1.2552668253924462
      }
    }
  },
  {
    "obj_attr": "static",
    "obj_id": "45",
    "obj_type": "Motorcycle",
    "psr": {
      "position": {
        "x": -15.594268914387047,
        "y": -6.383463872109106,
        "z": -1.1236583002885185
      },
      "rotation": {
        "x": 0,
        "y": 0,
        "z": -1.5448435364974658
      },
      "scale": {
        "x": 1.4726687749200402,
        "y": 0.450066437063754,
        "z": 1.3726130047602285
      }
    }
  },
  {
    "obj_attr": "static",
    "obj_id": "46",
    "obj_type": "Motorcycle",
    "psr": {
      "position": {
        "x": -9.627148922197453,
        "y": -6.27135069065807,
        "z": -1.2902883899449242
      },
      "rotation": {
        "x": 0,
        "y": 0,
        "z": -1.5446163880149815
      },
      "scale": {
        "x": 1.606990799132909,
        "y": 0.5491740302156917,
        "z": 1.5151511215583768
      }
    }
  },
  {
    "obj_attr": "static",
    "obj_id": "47",
    "obj_type": "Motorcycle",
    "psr": {
      "position": {
        "x": -8.910852386336476,
        "y": -6.232613666813285,
        "z": -1.2932583644484992
      },
      "rotation": {
        "x": 0,
        "y": 0,
        "z": -1.575340395522912
      },
      "scale": {
        "x": 1.5279954371201094,
        "y": 0.5566076794785355,
        "z": 1.4463313722557898
      }
    }
  },
  {
    "obj_attr": "static",
    "obj_id": "48",
    "obj_type": "Motorcycle",
    "psr": {
      "position": {
        "x": -8.336222899644989,
        "y": -6.1715226525500935,
        "z": -1.2932583644484992
      },
      "rotation": {
        "x": 0,
        "y": 0,
        "z": -1.5468632570024687
      },
      "scale": {
        "x": 1.4313699930863877,
        "y": 0.6073510311198365,
        "z": 1.4463313722557898
      }
    }
  },
  {
    "obj_attr": "static",
    "obj_id": "49",
    "obj_type": "Motorcycle",
    "psr": {
      "position": {
        "x": -16.306659896772878,
        "y": -6.322557092449488,
        "z": -1.1089093135760517
      },
      "rotation": {
        "x": 0,
        "y": 0,
        "z": -1.511265989074792
      },
      "scale": {
        "x": 1.3738958139510506,
        "y": 0.6332317920987589,
        "z": 1.4365208528364557
      }
    }
  },
  {
    "obj_attr": "static",
    "obj_id": "50",
    "obj_type": "Motorcycle",
    "psr": {
      "position": {
        "x": -16.933396860402862,
        "y": -6.345108835714856,
        "z": -1.2072336778202652
      },
      "rotation": {
        "x": 0,
        "y": 0,
        "z": -1.654021410980988
      },
      "scale": {
        "x": 1.3879634971774608,
        "y": 0.5239698197052015,
        "z": 1.2742819989993222
      }
    }
  },
  {
    "obj_attr": "static",
    "obj_id": "51",
    "obj_type": "Motorcycle",
    "psr": {
      "position": {
        "x": -7.498305469397789,
        "y": -6.1348057657776796,
        "z": -1.14754587545258
      },
      "rotation": {
        "x": 0,
        "y": 0,
        "z": -1.540974653046807
      },
      "scale": {
        "x": 1.4409008730752715,
        "y": 0.7951819829737734,
        "z": 1.4463313722557898
      }
    }
  },
  {
    "obj_attr": "static",
    "obj_id": "101",
    "obj_type": "Truck",
    "psr": {
      "position": {
        "x": -38.964681793434494,
        "y": -5.698129351504898,
        "z": -0.08038460661437605
      },
      "rotation": {
        "x": 0,
        "y": 0,
        "z": 0.0937293427171679
      },
      "scale": {
        "x": 6.605273666981843,
        "y": 4.012823383780391,
        "z": 3.1386635194116135
      }
    }
  },
  {
    "obj_attr": "",
    "obj_id": "102",
    "obj_type": "Truck",
    "psr": {
      "position": {
        "x": -0.12511470242500683,
        "y": -3.2923564666032186,
        "z": -0.958171388825836
      },
      "rotation": {
        "x": 0,
        "y": 0,
        "z": 0.02617993877991494
      },
      "scale": {
        "x": 5.187039539812092,
        "y": 2.8,
        "z": 1.9573145187319563
      }
    }
  },
  {
    "obj_attr": "static",
    "obj_id": "103",
    "obj_type": "Truck",
    "psr": {
      "position": {
        "x": 16.456659534385725,
        "y": -4.256566269048515,
        "z": -0.8287428282182379
      },
      "rotation": {
        "x": 0,
        "y": 0,
        "z": 0.11669503727759047
      },
      "scale": {
        "x": 5.389084720340623,
        "y": 2.183760200099039,
        "z": 2.6833927674557527
      }
    }
  },
  {
    "obj_attr": "",
    "obj_id": "104",
    "obj_type": "Truck",
    "psr": {
      "position": {
        "x": 9.487291610464041,
        "y": 3.7270773580899443,
        "z": -0.6410867448089891
      },
      "rotation": {
        "x": 0,
        "y": 0,
        "z": -3.115412714809878
      },
      "scale": {
        "x": 5.473384459113753,
        "y": 2.54186254071811,
        "z": 2.3226595869537934
      }
    }
  },
  {
    "obj_attr": "static",
    "obj_id": "200",
    "obj_type": "Car",
    "psr": {
      "position": {
        "x": 6.660769751110949,
        "y": -7.007161018304706,
        "z": -1.1873852451190428
      },
      "rotation": {
        "x": 0,
        "y": 0,
        "z": -0.8176408518882332
      },
      "scale": {
        "x": 4.709586336666417,
        "y": 2.0209651067402463,
        "z": 1.608013538429156
      }
    }
  },
  {
    "obj_attr": "",
    "obj_id": "201",
    "obj_type": "Car",
    "psr": {
      "position": {
        "x": 53.47790891228294,
        "y": 1.8004312953528103,
        "z": -1.532250150037934
      },
      "rotation": {
        "x": 0,
        "y": 0,
        "z": 0.026887263394568282
      },
      "scale": {
        "x": 4.68969547428207,
        "y": 1.972013204583337,
        "z": 1.6277779022716077
      }
    }
  },
  {
    "obj_attr": "",
    "obj_id": "204",
    "obj_type": "Car",
    "psr": {
      "position": {
        "x": -66.72850202645951,
        "y": 0.8565478515049872,
        "z": -0.6264659923465996
      },
      "rotation": {
        "x": 0,
        "y": 0,
        "z": -3.115412714809878
      },
      "scale": {
        "x": 4.789149786203808,
        "y": 2.1219318665705176,
        "z": 1.887619443076183
      }
    }
  },
  {
    "obj_attr": "",
    "obj_id": "205",
    "obj_type": "Car",
    "psr": {
      "position": {
        "x": -31.939528474343668,
        "y": 2.5348220230647036,
        "z": -0.8062343299388885
      },
      "rotation": {
        "x": 0,
        "y": 0,
        "z": -3.024224346381747
      },
      "scale": {
        "x": 4.789149786203808,
        "y": 1.7638963436522601,
        "z": 1.8166047185659409
      }
    }
  },
  {
    "obj_attr": "",
    "obj_id": "206",
    "obj_type": "Car",
    "psr": {
      "position": {
        "x": -7.858632929032675,
        "y": 3.229088269122379,
        "z": -1.084144139967125
      },
      "rotation": {
        "x": 0,
        "y": 0,
        "z": -3.115412714809878
      },
      "scale": {
        "x": 5.915180094885937,
        "y": 1.7253108869986051,
        "z": 1.5037179483607637
      }
    }
  },
  {
    "obj_attr": "",
    "obj_id": "207",
    "obj_type": "Car",
    "psr": {
      "position": {
        "x": 26.97627410420932,
        "y": 3.928469820467723,
        "z": -1.2259361669421196
      },
      "rotation": {
        "x": 0,
        "y": 0,
        "z": -3.115412714809878
      },
      "scale": {
        "x": 4.889166843754609,
        "y": 2.300949628029646,
        "z": 1.8166047185659409
      }
    }
  },
  {
    "obj_attr": "",
    "obj_id": "208",
    "obj_type": "Car",
    "psr": {
      "position": {
        "x": 57.93770397812175,
        "y": 4.989239565010347,
        "z": -1.6576895418745392
      },
      "rotation": {
        "x": 0,
        "y": 0,
        "z": -3.115412714809878
      },
      "scale": {
        "x": 4.284239575319948,
        "y": 2.1820958504040493,
        "z": 1.6008026428009887
      }
    }
  },
  {
    "obj_attr": "",
    "obj_id": "300",
    "obj_type": "MotorcyleRider",
    "psr": {
      "position": {
        "x": -26.38254401234431,
        "y": -1.8750200089241345,
        "z": -0.7688836701201899
      },
      "rotation": {
        "x": 0,
        "y": 0,
        "z": 0.10296294636858001
      },
      "scale": {
        "x": 2.0878163151093587,
        "y": 0.839146558234248,
        "z": 1.6517042199116108
      }
    }
  },
  {
    "obj_attr": "",
    "obj_id": "303",
    "obj_type": "MotorcyleRider",
    "psr": {
      "position": {
        "x": -14.770679129599463,
        "y": -1.0852162263204705,
        "z": -0.9256071357846948
      },
      "rotation": {
        "x": 0,
        "y": 0,
        "z": 0.02617993877991494
      },
      "scale": {
        "x": 1.436015297949143,
        "y": 0.735721663952062,
        "z": 1.561365735316414
      }
    }
  },
  {
    "obj_attr": "",
    "obj_id": "304",
    "obj_type": "MotorcyleRider",
    "psr": {
      "position": {
        "x": -9.043803505662071,
        "y": -1.2663002636006908,
        "z": -0.9779619077573238
      },
      "rotation": {
        "x": 0,
        "y": 0,
        "z": 0.1308996938995747
      },
      "scale": {
        "x": 1.7099309839956283,
        "y": 0.8254732491673248,
        "z": 1.577107061888778
      }
    }
  },
  {
    "obj_attr": "",
    "obj_id": "305",
    "obj_type": "MotorcyleRider",
    "psr": {
      "position": {
        "x": -27.489637079282776,
        "y": -0.605008225227619,
        "z": -0.7495048589406452
      },
      "rotation": {
        "x": 0,
        "y": 0,
        "z": 0.02617993877991494
      },
      "scale": {
        "x": 2.0258504215753517,
        "y": 0.7196943307637291,
        "z": 1.5921772106874204
      }
    }
  },
  {
    "obj_attr": "",
    "obj_id": "306",
    "obj_type": "MotorcyleRider",
    "psr": {
      "position": {
        "x": 7.775125053077985,
        "y": -0.6193233105226459,
        "z": -1.3443223019213637
      },
      "rotation": {
        "x": 0,
        "y": 0,
        "z": -0.02617993877991509
      },
      "scale": {
        "x": 2.0878163151093587,
        "y": 0.9468723625927912,
        "z": 2.0694537321271818
      }
    }
  },
  {
    "obj_attr": "",
    "obj_id": "307",
    "obj_type": "MotorcyleRider",
    "psr": {
      "position": {
        "x": 46.41029244059847,
        "y": 0.3563155371489029,
        "z": -1.4292806884985851
      },
      "rotation": {
        "x": 0,
        "y": 0,
        "z": 0.02617993877991494
      },
      "scale": {
        "x": 1.8554677598909792,
        "y": 0.7878240090593571,
        "z": 1.5455461693344617
      }
    }
  },
  {
    "obj_attr": "",
    "obj_id": "308",
    "obj_type": "MotorcyleRider",
    "psr": {
      "position": {
        "x": 35.71988069702113,
        "y": -3.688660685047129,
        "z": -1.4136718548255274
      },
      "rotation": {
        "x": 0,
        "y": 0,
        "z": 0.02617993877991494
      },
      "scale": {
        "x": 2.0878163151093587,
        "y": 1.0815859318396106,
        "z": 1.6760146082889058
      }
    }
  },
  {
    "obj_attr": "",
    "obj_id": "309",
    "obj_type": "MotorcyleRider",
    "psr": {
      "position": {
        "x": -51.31948906204678,
        "y": -2.629170458446433,
        "z": -0.5925467453964297
      },
      "rotation": {
        "x": 0,
        "y": 0,
        "z": -0.02617993877991509
      },
      "scale": {
        "x": 2.0878163151093587,
        "y": 0.9468723625927912,
        "z": 1.5640173156304316
      }
    }
  },
  {
    "obj_attr": "",
    "obj_id": "310",
    "obj_type": "MotorcyleRider",
    "psr": {
      "position": {
        "x": -60.349160096824306,
        "y": -2.2356929739338,
        "z": -0.6037066071466793
      },
      "rotation": {
        "x": 0,
        "y": 0,
        "z": 0.1308996938995747
      },
      "scale": {
        "x": 2.0878163151093587,
        "y": 0.6719249553973745,
        "z": 1.6509590624245385
      }
    }
  },
  {
    "obj_attr": "",
    "obj_id": "318",
    "obj_type": "MotorcyleRider",
    "psr": {
      "position": {
        "x": -27.64640818546001,
        "y": 1.318750341517196,
        "z": -0.6350831447626994
      },
      "rotation": {
        "x": 0,
        "y": 0,
        "z": -3.115412714809878
      },
      "scale": {
        "x": 1.5475679760097434,
        "y": 0.9468723625927912,
        "z": 2.0694537321271818
      }
    }
  },
  {
    "obj_attr": "",
    "obj_id": "319",
    "obj_type": "MotorcyleRider",
    "psr": {
      "position": {
        "x": -20.44998501819685,
        "y": 4.59653829256169,
        "z": -0.9206534847617149
      },
      "rotation": {
        "x": 0,
        "y": 0,
        "z": -3.0630528372500483
      },
      "scale": {
        "x": 1.557323021186678,
        "y": 0.7076358306985888,
        "z": 1.5923127681016922
      }
    }
  },
  {
    "obj_attr": "",
    "obj_id": "320",
    "obj_type": "MotorcyleRider",
    "psr": {
      "position": {
        "x": -28.992787004490594,
        "y": 4.73714519959457,
        "z": -0.7360266465887948
      },
      "rotation": {
        "x": 0,
        "y": 0,
        "z": -3.126492593795204
      },
      "scale": {
        "x": 1.6191818029250535,
        "y": 0.9468723625927912,
        "z": 1.9581623158305952
      }
    }
  },
  {
    "obj_attr": "static",
    "obj_id": "407",
    "obj_type": "Pedestrian",
    "psr": {
      "position": {
        "x": -12.837125421987832,
        "y": -11.345023149472812,
        "z": -0.482692592301409
      },
      "rotation": {
        "x": 0,
        "y": 0,
        "z": -1.6006402617151014
      },
      "scale": {
        "x": 0.664616136589408,
        "y": 0.5487005710027502,
        "z": 1.7227505879744966
      }
    }
  },
  {
    "obj_attr": "static",
    "obj_id": "409",
    "obj_type": "Pedestrian",
    "psr": {
      "position": {
        "x": 9.56974899777921,
        "y": -7.7782254946722,
        "z": -1.0649665113082867
      },
      "rotation": {
        "x": 0,
        "y": 0,
        "z": -1.6006402617151014
      },
      "scale": {
        "x": 0.5340120204170653,
        "y": 0.43391695499154687,
        "z": 1.774520995283868
      }
    }
  },
  {
    "obj_attr": "static",
    "obj_id": "410",
    "obj_type": "Pedestrian",
    "psr": {
      "position": {
        "x": 14.564590605741206,
        "y": -9.857051934063534,
        "z": -0.707828351000155
      },
      "rotation": {
        "x": 0,
        "y": 0,
        "z": -1.0266472494286412
      },
      "scale": {
        "x": 0.42548215126179717,
        "y": 0.5937229829627185,
        "z": 1.6914306966406254
      }
    }
  },
  {
    "obj_attr": "static",
    "obj_id": "411",
    "obj_type": "Pedestrian",
    "psr": {
      "position": {
        "x": 13.272318274351168,
        "y": -10.411231411944591,
        "z": -1.1999078759089814
      },
      "rotation": {
        "x": 0,
        "y": 0,
        "z": -1.6006402617151014
      },
      "scale": {
        "x": 0.5078921214937105,
        "y": 0.44559358323052745,
        "z": 1.5046382660824789
      }
    }
  },
  {
    "obj_attr": "static",
    "obj_id": "412",
    "obj_type": "Pedestrian",
    "psr": {
      "position": {
        "x": 12.651837507145332,
        "y": -14.864334996615222,
        "z": -1.1376249019224123
      },
      "rotation": {
        "x": 0,
        "y": 0,
        "z": -0.7313008293264601
      },
      "scale": {
        "x": 0.27767018624354206,
        "y": 0.6087153724464053,
        "z": 1.6292042140556167
      }
    }
  },
  {
    "obj_attr": "static",
    "obj_id": "423",
    "obj_type": "Pedestrian",
    "psr": {
      "position": {
        "x": -0.3988056329597244,
        "y": 7.561876614161786,
        "z": -1.0649665113082867
      },
      "rotation": {
        "x": 0,
        "y": 0,
        "z": 2.1533134103987366
      },
      "scale": {
        "x": 0.4458887622395184,
        "y": 0.5755746868300204,
        "z": 1.774520995283868
      }
    }
  },
  {
    "obj_id": "424",
    "obj_type": "Pedestrian",
    "psr": {
      "position": {
        "x": 6.899531793894003,
        "y": 8.958766191241015,
        "z": -1.0387750298120653
      },
      "rotation": {
        "x": 0,
        "y": 0,
        "z": -2.801253449450899
      },
      "scale": {
        "x": 0.7098367012195931,
        "y": 0.6040242377902483,
        "z": 1.906520718268936
      }
    }
  },
  {
    "obj_attr": "",
    "obj_id": "425",
    "obj_type": "Pedestrian",
    "psr": {
      "position": {
        "x": 6.026898641164793,
        "y": 11.727331737006637,
        "z": -1.0649665113082867
      },
      "rotation": {
        "x": 0,
        "y": 0,
        "z": -1.6006402617151014
      },
      "scale": {
        "x": 0.36122104719797543,
        "y": 0.6796528730632951,
        "z": 1.774520995283868
      }
    }
  },
  {
    "obj_attr": "",
    "obj_id": "427",
    "obj_type": "Pedestrian",
    "psr": {
      "position": {
        "x": 4.94812213461575,
        "y": 11.604167678615603,
        "z": -1.0649665113082867
      },
      "rotation": {
        "x": 0,
        "y": 0,
        "z": -1.6006402617151014
      },
      "scale": {
        "x": 0.4487993253041367,
        "y": 0.30745203451733893,
        "z": 1.774520995283868
      }
    }
  }
]